{"cameraMode":{"drawMode":0,"name":"Shaded","section":"Shading Mode"},"sceneLighting":true,"audioPlay":false,"sceneViewState":{"showFog":true,"showMaterialUpdate":false,"showSkybox":true,"showFlares":true,"showImageEffects":true,"showParticleSystems":true},"in2DMode":false,"pivot":{"x":4.050682544708252,"y":1.5701888799667359,"z":5.367692947387695},"rotation":{"x":0.13907122611999513,"y":0.7941567897796631,"z":-0.19813519716262818,"w":0.5574196577072144},"size":4.459951877593994,"orthographic":false}